[{"type": "Feature", "properties": {"N02_001": "21", "N02_002": "4", "N02_003": "\u652f\u7dda", "N02_004": "\u5bcc\u5c71\u5730\u65b9\u9244\u9053", "N02_005": "\u4e38\u306e\u5185"}, "geometry": {"type": "LineString", "coordinates": [[137.20895, 36.69271], [137.20893, 36.6923]]}} , {"type": "Feature", "properties": {"N02_001": "21", "N02_002": "4", "N02_003": "\u652f\u7dda", "N02_004": "\u5bcc\u5c71\u5730\u65b9\u9244\u9053", "N02_005": "\u65b0\u5bcc\u753a"}, "geometry": {"type": "LineString", "coordinates": [[137.21156, 36.69905], [137.21131, 36.69867]]}} , {"type": "Feature", "properties": {"N02_001": "21", "N02_002": "4", "N02_003": "\u652f\u7dda", "N02_004": "\u5bcc\u5c71\u5730\u65b9\u9244\u9053", "N02_005": "\u770c\u5e81\u524d"}, "geometry": {"type": "LineString", "coordinates": [[137.20981, 36.69578], [137.20968, 36.69538]]}} , {"type": "Feature", "properties": {"N02_001": "21", "N02_002": "4", "N02_003": "\u652f\u7dda", "N02_004": "\u5bcc\u5c71\u5730\u65b9\u9244\u9053", "N02_005": "\u96fb\u9244\u5bcc\u5c71\u99c5\u30fb\u30a8\u30b9\u30bf\u524d"}, "geometry": {"type": "LineString", "coordinates": [[137.21431, 36.6998], [137.21382, 36.70001]]}}]