[{"type": "Feature", "properties": {"N02_001": "21", "N02_002": "4", "N02_003": "\u672c\u7dda", "N02_004": "\u9577\u5d0e\u96fb\u6c17\u8ecc\u9053", "N02_005": "\u6d66\u4e0a\u99c5\u524d"}, "geometry": {"type": "LineString", "coordinates": [[129.86415, 32.76524], [129.86413, 32.76571]]}} , {"type": "Feature", "properties": {"N02_001": "21", "N02_002": "4", "N02_003": "\u672c\u7dda", "N02_004": "\u9577\u5d0e\u96fb\u6c17\u8ecc\u9053", "N02_005": "\u5927\u6ce2\u6b62"}, "geometry": {"type": "LineString", "coordinates": [[129.87208, 32.7457], [129.87204, 32.74558]]}} , {"type": "Feature", "properties": {"N02_001": "21", "N02_002": "4", "N02_003": "\u672c\u7dda", "N02_004": "\u9577\u5d0e\u96fb\u6c17\u8ecc\u9053", "N02_005": "\u5d07\u798f\u5bfa"}, "geometry": {"type": "LineString", "coordinates": [[129.88279, 32.74099], [129.88238, 32.74125]]}} , {"type": "Feature", "properties": {"N02_001": "21", "N02_002": "4", "N02_003": "\u672c\u7dda", "N02_004": "\u9577\u5d0e\u96fb\u6c17\u8ecc\u9053", "N02_005": "\u4e94\u5cf6\u753a"}, "geometry": {"type": "LineString", "coordinates": [[129.87222, 32.74934], [129.87222, 32.74926], [129.87223, 32.7492]]}} , {"type": "Feature", "properties": {"N02_001": "21", "N02_002": "4", "N02_003": "\u672c\u7dda", "N02_004": "\u9577\u5d0e\u96fb\u6c17\u8ecc\u9053", "N02_005": "\u82e5\u8449\u753a"}, "geometry": {"type": "LineString", "coordinates": [[129.861674, 32.787751], [129.861818, 32.787326]]}} , {"type": "Feature", "properties": {"N02_001": "21", "N02_002": "4", "N02_003": "\u672c\u7dda", "N02_004": "\u9577\u5d0e\u96fb\u6c17\u8ecc\u9053", "N02_005": "\u65b0\u5730\u4e2d\u83ef\u8857"}, "geometry": {"type": "LineString", "coordinates": [[129.8751, 32.74301], [129.87478, 32.74266]]}} , {"type": "Feature", "properties": {"N02_001": "21", "N02_002": "4", "N02_003": "\u672c\u7dda", "N02_004": "\u9577\u5d0e\u96fb\u6c17\u8ecc\u9053", "N02_005": "\u539f\u7206\u8cc7\u6599\u9928"}, "geometry": {"type": "LineString", "coordinates": [[129.86348, 32.77063], [129.86364, 32.77049]]}} , {"type": "Feature", "properties": {"N02_001": "21", "N02_002": "4", "N02_003": "\u672c\u7dda", "N02_004": "\u9577\u5d0e\u96fb\u6c17\u8ecc\u9053", "N02_005": "\u5343\u6b73\u753a"}, "geometry": {"type": "LineString", "coordinates": [[129.86126, 32.78903], [129.86111, 32.78948]]}} , {"type": "Feature", "properties": {"N02_001": "21", "N02_002": "4", "N02_003": "\u672c\u7dda", "N02_004": "\u9577\u5d0e\u96fb\u6c17\u8ecc\u9053", "N02_005": "\u6d66\u4e0a\u8eca\u5eab"}, "geometry": {"type": "LineString", "coordinates": [[129.86132, 32.7792], [129.86138, 32.77946], [129.86144, 32.77965], [129.86155, 32.77986]]}} , {"type": "Feature", "properties": {"N02_001": "21", "N02_002": "4", "N02_003": "\u672c\u7dda", "N02_004": "\u9577\u5d0e\u96fb\u6c17\u8ecc\u9053", "N02_005": "\u92ad\u5ea7\u753a"}, "geometry": {"type": "LineString", "coordinates": [[129.86574, 32.76109], [129.86567, 32.76156]]}} , {"type": "Feature", "properties": {"N02_001": "21", "N02_002": "4", "N02_003": "\u672c\u7dda", "N02_004": "\u9577\u5d0e\u96fb\u6c17\u8ecc\u9053", "N02_005": "\u9577\u5d0e\u5927\u5b66"}, "geometry": {"type": "LineString", "coordinates": [[129.86245, 32.7847], [129.86245, 32.78517]]}} , {"type": "Feature", "properties": {"N02_001": "21", "N02_002": "4", "N02_003": "\u672c\u7dda", "N02_004": "\u9577\u5d0e\u96fb\u6c17\u8ecc\u9053", "N02_005": "\u4f4f\u5409"}, "geometry": {"type": "LineString", "coordinates": [[129.86002, 32.79178], [129.85974, 32.7922]]}} , {"type": "Feature", "properties": {"N02_001": "21", "N02_002": "4", "N02_003": "\u672c\u7dda", "N02_004": "\u9577\u5d0e\u96fb\u6c17\u8ecc\u9053", "N02_005": "\u5e73\u548c\u516c\u5712"}, "geometry": {"type": "LineString", "coordinates": [[129.86206, 32.77416], [129.86196, 32.77482]]}} , {"type": "Feature", "properties": {"N02_001": "21", "N02_002": "4", "N02_003": "\u672c\u7dda", "N02_004": "\u9577\u5d0e\u96fb\u6c17\u8ecc\u9053", "N02_005": "\u5ca9\u5c4b\u6a4b"}, "geometry": {"type": "LineString", "coordinates": [[129.86238, 32.78217], [129.86239, 32.78251]]}} , {"type": "Feature", "properties": {"N02_001": "21", "N02_002": "4", "N02_003": "\u672c\u7dda", "N02_004": "\u9577\u5d0e\u96fb\u6c17\u8ecc\u9053", "N02_005": "\u5b9d\u753a"}, "geometry": {"type": "LineString", "coordinates": [[129.86882, 32.75794], [129.86842, 32.75827]]}} , {"type": "Feature", "properties": {"N02_001": "21", "N02_002": "4", "N02_003": "\u672c\u7dda", "N02_004": "\u9577\u5d0e\u96fb\u6c17\u8ecc\u9053", "N02_005": "\u5927\u5b66\u75c5\u9662"}, "geometry": {"type": "LineString", "coordinates": [[129.86409, 32.7689], [129.86408, 32.76936]]}} , {"type": "Feature", "properties": {"N02_001": "21", "N02_002": "4", "N02_003": "\u672c\u7dda", "N02_004": "\u9577\u5d0e\u96fb\u6c17\u8ecc\u9053", "N02_005": "\u89b3\u5149\u901a"}, "geometry": {"type": "LineString", "coordinates": [[129.87803, 32.74331], [129.87754, 32.74352]]}} , {"type": "Feature", "properties": {"N02_001": "21", "N02_002": "4", "N02_003": "\u672c\u7dda", "N02_004": "\u9577\u5d0e\u96fb\u6c17\u8ecc\u9053", "N02_005": "\u897f\u6d5c\u753a"}, "geometry": {"type": "LineString", "coordinates": [[129.87624, 32.74385], [129.87584, 32.74359]]}} , {"type": "Feature", "properties": {"N02_001": "21", "N02_002": "4", "N02_003": "\u672c\u7dda", "N02_004": "\u9577\u5d0e\u96fb\u6c17\u8ecc\u9053", "N02_005": "\u662d\u548c\u753a\u901a"}, "geometry": {"type": "LineString", "coordinates": [[129.86079, 32.79032], [129.86062, 32.79075]]}} , {"type": "Feature", "properties": {"N02_001": "21", "N02_002": "4", "N02_003": "\u672c\u7dda", "N02_004": "\u9577\u5d0e\u96fb\u6c17\u8ecc\u9053", "N02_005": "\u5927\u6a4b"}, "geometry": {"type": "LineString", "coordinates": [[129.86157, 32.77721], [129.86146, 32.77792]]}} , {"type": "Feature", "properties": {"N02_001": "21", "N02_002": "4", "N02_003": "\u672c\u7dda", "N02_004": "\u9577\u5d0e\u96fb\u6c17\u8ecc\u9053", "N02_005": "\u8302\u91cc\u753a"}, "geometry": {"type": "LineString", "coordinates": [[129.86456, 32.76376], [129.86442, 32.7642]]}} , {"type": "Feature", "properties": {"N02_001": "21", "N02_002": "4", "N02_003": "\u672c\u7dda", "N02_004": "\u9577\u5d0e\u96fb\u6c17\u8ecc\u9053", "N02_005": "\u601d\u6848\u6a4b"}, "geometry": {"type": "LineString", "coordinates": [[129.8806, 32.74261], [129.88008, 32.74274]]}} , {"type": "Feature", "properties": {"N02_001": "21", "N02_002": "4", "N02_003": "\u672c\u7dda", "N02_004": "\u9577\u5d0e\u96fb\u6c17\u8ecc\u9053", "N02_005": "\u51fa\u5cf6"}, "geometry": {"type": "LineString", "coordinates": [[129.87184, 32.74368], [129.87181, 32.74382], [129.87179, 32.74397], [129.87179, 32.74414]]}} , {"type": "Feature", "properties": {"N02_001": "21", "N02_002": "4", "N02_003": "\u672c\u7dda", "N02_004": "\u9577\u5d0e\u96fb\u6c17\u8ecc\u9053", "N02_005": "\u9577\u5d0e\u99c5\u524d"}, "geometry": {"type": "LineString", "coordinates": [[129.87168, 32.75282], [129.87196, 32.75229]]}} , {"type": "Feature", "properties": {"N02_001": "21", "N02_002": "4", "N02_003": "\u672c\u7dda", "N02_004": "\u9577\u5d0e\u96fb\u6c17\u8ecc\u9053", "N02_005": "\u516b\u5343\u4ee3\u753a"}, "geometry": {"type": "LineString", "coordinates": [[129.8705, 32.7543], [129.87034, 32.75491]]}}]